Workbook
Name Slicer_Category: #N/A
Name Slicer_Order_Month: #N/A

Sheet Raw_Data
A1: Order_ID | B1: Order_Date | C1: Customer_ID | D1: Customer_Name | E1: City | F1: Product_ID | G1: Product_Name | H1: Category | I1: Quantity | J1: Unit_Price | K1: Total_Amount | L1: Payment_Method | M1: Payment_Status | N1: Order_Status | O1: Expected_Delivery_Date | P1: Actual_Delivery_Date | Q1: Delivery_Partner | R1: Return_Reason | S1: Cancellation_Reason
A2: ORD001 | B2: 46295 | C2: C007 | D2: Suresh | E2: Tenkasi | F2: P018 | G2: Office File | H2: Stationery | I2: 2 | J2: 120 | K2: 240 | L2: Debit Card | M2: Pending | N2: Delivered | O2: 46300 | P2: 46301 | Q2: Ecom Express
A3: ORD002 | B3: 46235 | C3: C017 | D3: Vijay | E3: Erode | F3: P015 | G3: Cookware Set | H3: Home & Kitchen | I3: 1 | J3: 3200 | K3: 3200 | L3: Debit Card | M3: Failed | N3: Cancelled | O3: 46239 | Q3: BlueDart | S3: Delivery delay
A4: ORD003 | B4: 46204 | C4: C018 | D4: Harini | E4: Coimbatore | F4: P008 | G4: Laptop Stand | H4: Electronics | I4: 2 | J4: 1100 | K4: 2200 | L4: UPI | M4: Pending | N4: Delivered | O4: 46207 | P4: 46209 | Q4: Delhivery
A5: ORD004 | B5: 46213 | C5: C003 | D5: Rahul | E5: Coimbatore | F5: P002 | G5: Keyboard | H5: Electronics | I5: 3 | J5: 850 | K5: 2550 | L5: Debit Card | M5: Paid | N5: Returned | O5: 46220 | P5: 46220 | Q5: Ecom Express | R5: Wrong product
A6: ORD005 | B6: 46235 | C6: C018 | D6: Harini | E6: Coimbatore | F6: P005 | G6: USB Cable | H6: Electronics | I6: 4 | J6: 350 | K6: 1400 | L6: Credit Card | M6: Paid | N6: Delivered | O6: 46241 | P6: 46244 | Q6: BlueDart
A7: ORD006 | B7: 46258 | C7: C004 | D7: Divya | E7: Trichy | F7: P014 | G7: Water Bottle | H7: Home & Kitchen | I7: 3 | J7: 500 | K7: 1500 | L7: UPI | M7: Paid | N7: Shipped | O7: 46264 | Q7: BlueDart
A8: ORD007 | B8: 46217 | C8: C002 | D8: Priya | E8: Madurai | F8: P013 | G8: Bedsheet | H8: Home & Kitchen | I8: 3 | J8: 950 | K8: 2850 | L8: Net Banking | M8: Paid | N8: Delivered | O8: 46221 | P8: 46221 | Q8: Ecom Express
A9: ORD008 | B9: 46239 | C9: C005 | D9: Karthik | E9: chennai | F9: P014 | G9: Water Bottle | H9: Home & Kitchen | I9: 2 | J9: 500 | K9: 1000 | L9: Cash on Delivery | M9: Paid | N9: Delivered | O9: 46245 | P9: 46245 | Q9: BlueDart
A10: ORD009 | B10: 46215 | C10: C002 | D10: Priya | E10: Madurai | F10: P018 | G10: Office File | H10: Stationery | I10: 1 | J10: 120 | K10: 120 | L10: Cash on Delivery | M10: Paid | N10: Delivered | O10: 46219 | P10: 46219 | Q10: Ecom Express
A11: ORD010 | B11: 46225 | C11: C007 | D11: Suresh | E11: Tenkasi | F11: P013 | G11: Bedsheet | H11: Home & Kitchen | I11: 1 | J11: 950 | K11: 950 | L11: Debit Card | M11: Paid | N11: Delivered | O11: 46231 | P11: 46230 | Q11: Ecom Express
A12: ORD011 | B12: 46223 | C12: C010 | D12: Asha | E12: Madurai | F12: P014 | G12: Water Bottle | H12: Home & Kitchen | I12: 4 | J12: 500 | K12: 2000 | L12: Credit Card | M12: Paid | N12: Shipped | O12: 46227 | Q12: BlueDart
A13: ORD012 | B13: 46244 | C13: C019 | D13: Prakash | E13: Salem | F13: P018 | G13: Office File | H13: Stationery | I13: 1 | J13: 120 | K13: 120 | L13: Net Banking | M13: Paid | N13: Placed | O13: 46247 | Q13: Ecom Express
A14: ORD013 | B14: 46211 | C14: C017 | D14: Vijay | E14: Erode | F14: P017 | G14: Notebook | H14: Stationery | I14: 2 | J14: 180 | K14: 360 | L14: Credit Card | M14: Paid | N14: Shipped | O14: 46218 | Q14: BlueDart
A15: ORD014 | B15: 46255 | C15: C020 | D15: Fathima | E15: Tirunelveli | F15: P003 | G15: Bluetooth Speaker | H15: Electronics | I15: 2 | J15: 1450 | K15: 2900 | L15: Net Banking | M15: Paid | N15: Delivered | O15: 46258 | P15: 46259 | Q15: BlueDart
A16: ORD015 | B16: 46288 | C16: C020 | D16: Fathima | E16: Tirunelveli | F16: P003 | G16: Bluetooth Speaker | H16: Electronics | I16: 4 | J16: 1450 | K16: 5800 | L16: Net Banking | M16: Pending | N16: Confirmed | O16: 46295 | Q16: DTDC
A17: ORD016 | B17: 46234 | C17: C009 | D17: Vignesh | E17: Chennai | F17: P007 | G17: Smart Watch | H17: Electronics | I17: 3 | J17: 2500 | K17: 7500 | L17: Credit Card | M17: Paid | N17: Placed | O17: 46239 | Q17: DTDC
A18: ORD017 | B18: 46205 | C18: C015 | D18: Santhosh | E18: Chennai | F18: P011 | G18: Backpack | H18: Fashion | I18: 1 | J18: 1250 | K18: 1250 | L18: UPI | M18: Pending | N18: Delivered | O18: 46211 | P18: 46212 | Q18: BlueDart
A19: ORD018 | B19: 46220 | C19: C018 | D19: Harini | E19: Coimbatore | F19: P007 | G19: Smart Watch | H19: Electronics | I19: 3 | J19: 2500 | K19: 7500 | L19: Credit Card | M19: Paid | N19: Shipped | O19: 46225 | Q19: DTDC
A20: ORD019 | B20: 46273 | C20: C010 | D20: Asha | E20: Madurai | F20: P006 | G20: Power Bank | H20: Electronics | I20: 4 | J20: 1200 | K20: 4800 | L20: Net Banking | M20: Pending | N20: Delivered | O20: 46278 | P20: 46279 | Q20: BlueDart
A21: ORD020 | B21: 46221 | C21: C018 | D21: Harini | E21: Coimbatore | F21: P010 | G21: Jeans | H21: Fashion | I21: 1 | J21: 1400 | K21: 1400 | L21: Net Banking | M21: Paid | N21: Delivered | O21: 46226 | P21: 46225 | Q21: Delhivery
A22: ORD021 | B22: 46295 | C22: C009 | D22: Vignesh | E22: Chennai | F22: P010 | G22: Jeans | H22: Fashion | I22: 2 | J22: 1400 | K22: 2800 | L22: Debit Card | M22: Paid | N22: Confirmed | O22: 46300 | Q22: Ecom Express
A23: ORD022 | B23: 46285 | C23: C009 | D23: Vignesh | E23: Chennai | F23: P002 | G23: Keyboard | H23: Electronics | I23: 1 | J23: 850 | K23: 850 | L23: UPI | M23: Paid | N23: delivered | O23: 46291 | P23: 46294 | Q23: BlueDart
A24: ORD023 | B24: 46224 | C24: C011 | D24: Manoj | E24: Coimbatore | F24: P005 | G24: USB Cable | H24: Electronics | I24: 3 | J24: 350 | K24: 1050 | L24: Cash on Delivery | M24: Pending | N24: Delivered | O24: 46230 | P24: 46231 | Q24: BlueDart
A25: ORD024 | B25: 46273 | C25: C004 | D25: Divya | E25: Trichy | F25: P003 | G25: Bluetooth Speaker | H25: Electronics | I25: 2 | J25: 1450 | K25: 2900 | L25: Net Banking | M25: Paid | N25: Shipped | O25: 46276 | Q25: Delhivery
A26: ORD025 | B26: 46243 | C26: C014 | D26: Lavanya | E26: Tenkasi | F26: P005 | G26: USB Cable | H26: Electronics | I26: 1 | J26: 350 | K26: 350 | L26: Debit Card | M26: Failed | N26: Cancelled | O26: 46248 | Q26: Delhivery | S26: Payment issue
A27: ORD026 | B27: 46283 | C27: C004 | D27: Divya | E27: Trichy | F27: P012 | G27: Sports Shoes | H27: Fashion | I27: 4 | J27: 2200 | K27: 8800 | L27: Credit Card | M27: Paid | N27: Confirmed | O27: 46287 | Q27: Delhivery
A28: ORD027 | B28: 46246 | C28: C014 | D28: Lavanya | E28: Tenkasi | F28: P001 | G28: Wireless Mouse | H28: Electronics | I28: 2 | J28: 650 | K28: 1300 | L28: Credit Card | M28: Pending | N28: Delivered | O28: 46252 | P28: 46255 | Q28: DTDC
A29: ORD028 | B29: 46208 | C29: C006 | D29: Meena | E29: Tirunelveli | F29: P004 | G29: Headphones | H29: Electronics | I29: 4 | J29: 1800 | K29: 7200 | L29: Cash on Delivery | M29: Paid | N29: Delivered | O29: 46214 | P29: 46214 | Q29: DTDC
A30: ORD029 | B30: 46207 | C30: C010 | D30: Asha | E30: Madurai | F30: P008 | G30: Laptop Stand | H30: Electronics | I30: 2 | J30: 1100 | K30: 2200 | L30: Debit Card | M30: Paid | N30: Delivered | O30: 46211 | P30: 46212 | Q30: BlueDart
A31: ORD030 | B31: 46290 | C31: C009 | D31: Vignesh | E31: Chennai | F31: P012 | G31: Sports Shoes | H31: Fashion | I31: 4 | J31: 2200 | K31: 8800 | L31: UPI | M31: Paid | N31: Returned | O31: 46297 | P31: 46297 | Q31: BlueDart | R31: Product not as expected
A32: ORD031 | B32: 46208 | C32: C006 | D32: Meena | E32: Tirunelveli | F32: P019 | G32: Desk Organizer | H32: Stationery | I32: 3 | J32: 450 | K32: 1350 | L32: Debit Card | M32: Paid | N32: Delivered | O32: 46211 | P32: 46212 | Q32: DTDC
A33: ORD032 | B33: 46253 | C33: C014 | D33: Lavanya | E33: Tenkasi | F33: P020 | G33: Calculator | H33: Stationery | I33: 1 | J33: 550 | K33: 550 | L33: Debit Card | M33: Paid | N33: Shipped | O33: 46260 | Q33: BlueDart
A34: ORD033 | B34: 46250 | C34: C014 | D34: Lavanya | E34: Tenkasi | F34: P001 | G34: Wireless Mouse | H34: Electronics | I34: 2 | J34: 650 | K34: 1300 | L34: Debit Card | M34: Pending | N34: Delivered | O34: 46256 | P34: 46255 | Q34: DTDC
A35: ORD034 | B35: 46289 | C35: C004 | D35: Divya | E35: Trichy | F35: P010 | G35: Jeans | H35: Fashion | I35: 3 | J35: 1400 | K35: 4200 | L35: Debit Card | M35: Paid | N35: Delivered | O35: 46295 | P35: 46295 | Q35: Delhivery
A36: ORD035 | B36: 46290 | C36: C007 | D36: Suresh | E36: Tenkasi | F36: P014 | G36: Water Bottle | H36: Home & Kitchen | I36: 4 | J36: 500 | K36: 2000 | L36: Net Banking | M36: Pending | N36: Out for Delivery | O36: 46294 | Q36: DTDC
A37: ORD036 | B37: 46242 | C37: C013 | D37: Dinesh | E37: Tirunelveli | F37: P018 | G37: Office File | H37: Stationery | I37: 1 | J37: 120 | K37: 120 | L37: Net Banking | M37: Paid | N37: Delivered | O37: 46247 | P37: 46247 | Q37: DTDC
A38: ORD037 | B38: 46290 | C38: C015 | D38: Santhosh | E38: Chennai | F38: P015 | G38: Cookware Set | H38: Home & Kitchen | I38: 4 | J38: 3200 | K38: 12800 | L38: Credit Card | M38: Paid | N38: Delivered | O38: 46294 | P38: 46295 | Q38: BlueDart
A39: ORD038 | B39: 46215 | C39: C010 | D39: Asha | E39: Madurai | F39: P017 | G39: Notebook | H39: Stationery | I39: 3 | J39: 180 | K39: 540 | L39: Debit Card | M39: Paid | N39: Returned | O39: 46219 | P39: 46221 | Q39: Delhivery | R39: Wrong product
A40: ORD039 | B40: 46235 | C40: C005 | D40: Karthik | E40: Salem | F40: P001 | G40: Wireless Mouse | H40: Electronics | I40: 1 | J40: 650 | K40: 650 | L40: Cash on Delivery | M40: Paid | N40: Delivered | O40: 46241 | P40: 46242 | Q40: Ecom Express
A41: ORD040 | B41: 46267 | C41: C019 | D41: Prakash | E41: Salem | F41: P007 | G41: Smart Watch | H41: Electronics | I41: 4 | J41: 2500 | K41: 10000 | L41: Credit Card | M41: Paid | N41: Placed | O41: 46273 | Q41: BlueDart
A42: ORD041 | B42: 46226 | C42: C004 | D42: Divya | E42: Trichy | F42: P014 | G42: Water Bottle | H42: Home & Kitchen | I42: 2 | J42: 500 | K42: 1000 | L42: UPI | M42: Paid | N42: Placed | O42: 46233 | Q42: Delhivery
A43: ORD042 | B43: 46263 | C43: C004 | D43: Divya | E43: Trichy | F43: P015 | G43: Cookware Set | H43: Home & Kitchen | I43: 2 | J43: 3200 | K43: 6400 | L43: Debit Card | M43: Pending | N43: Delivered | O43: 46270 | P43: 46271 | Q43: Ecom Express
A44: ORD043 | B44: 46274 | C44: C020 | D44: Fathima | E44: Tirunelveli | F44: P017 | G44: Notebook | H44: Stationery | I44: 4 | J44: 180 | K44: 720 | L44: Cash on Delivery | M44: Pending | N44: Delivered | O44: 46280 | P44: 46280 | Q44: Ecom Express
A45: ORD044 | B45: 46270 | C45: C009 | D45: Vignesh | E45: Chennai | F45: P008 | G45: Laptop Stand | H45: Electronics | I45: 3 | J45: 1100 | K45: 3300 | L45: Credit Card | M45: Pending | N45: Out for Delivery | O45: 46276 | Q45: DTDC
A46: ORD045 | B46: 46234 | C46: C015 | D46: Santhosh | E46: Chennai | F46: P003 | G46: Bluetooth Speaker | H46: Electronics | I46: 3 | J46: 1450 | K46: 4350 | L46: upi | M46: Paid | N46: Confirmed | O46: 46239 | Q46: BlueDart
A47: ORD046 | B47: 46253 | C47: C005 | D47: Karthik | E47: Salem | F47: P005 | G47: USB Cable | H47: Electronics | I47: 2 | J47: 350 | K47: 700 | L47: UPI | M47: Paid | N47: Delivered | O47: 46257 | P47: 46259 | Q47: Ecom Express
A48: ORD047 | B48: 46257 | C48: C014 | D48: Lavanya | E48: Tenkasi | F48: P011 | G48: Backpack | H48: Fashion | I48: 4 | J48: 1250 | K48: 5000 | L48: Cash on Delivery | M48: Paid | N48: Shipped | O48: 46260 | Q48: Ecom Express
A49: ORD048 | B49: 46265 | C49: C019 | D49: Prakash | E49: Salem | F49: P001 | G49: Wireless Mouse | H49: Electronics | I49: 4 | J49: 650 | K49: 2600 | L49: Cash on Delivery | M49: Paid | N49: Delivered | O49: 46268 | P49: 46268 | Q49: Ecom Express
A50: ORD049 | B50: 46266 | C50: C018 | D50: Harini | E50: Coimbatore | F50: P018 | G50: Office File | H50: Stationery | I50: 2 | J50: 120 | K50: 240 | L50: Cash on Delivery | M50: Paid | N50: Delivered | O50: 46270 | P50: 46270 | Q50: BlueDart
A51: ORD050 | B51: 46225 | C51: C013 | D51: Dinesh | E51: Tirunelveli | F51: P011 | G51: Backpack | H51: Fashion | I51: 4 | J51: 1250 | K51: 5000 | L51: Net Banking | M51: Pending | N51: Delivered | O51: 46231 | P51: 46231 | Q51: BlueDart
A52: ORD051 | B52: 46214 | C52: C013 | D52: Dinesh | E52: Tirunelveli | F52: P019 | G52: Desk Organizer | H52: Stationery | I52: 1 | J52: 450 | K52: 450 | L52: Credit Card | M52: Paid | N52: Delivered | O52: 46220 | P52: 46220 | Q52: BlueDart
A53: ORD052 | B53: 46231 | C53: C009 | D53: Vignesh | E53: Chennai | F53: P013 | G53: Bedsheet | H53: Home & Kitchen | I53: 3 | J53: 950 | K53: 2850 | L53: Cash on Delivery | M53: Paid | N53: Delivered | O53: 46237 | P53: 46237 | Q53: DTDC
A54: ORD053 | B54: 46264 | C54: C014 | D54: Lavanya | E54: Tenkasi | F54: P009 | G54: T-Shirt | H54: Fashion | I54: 1 | J54: 700 | K54: 700 | L54: UPI | M54: Pending | N54: Delivered | O54: 46267 | P54: 46269 | Q54: DTDC
A55: ORD054 | B55: 46207 | C55: C008 | D55: Nisha | E55: Erode | F55: P003 | G55: Bluetooth Speaker | H55: Electronics | I55: 1 | J55: 1450 | K55: 1450 | L55: UPI | M55: Paid | N55: Out for Delivery | O55: 46211 | Q55: Delhivery
A56: ORD055 | B56: 46289 | C56: C008 | D56: Nisha | E56: Erode | F56: P005 | G56: USB Cable | H56: Electronics | I56: 4 | J56: 350 | K56: 1400 | L56: Cash on Delivery | M56: Paid | N56: Delivered | O56: 46292 | P56: 46293 | Q56: DTDC
A57: ORD056 | B57: 46224 | C57: C012 | D57: Keerthana | E57: Salem | F57: P006 | G57: Power Bank | H57: Electronics | I57: 1 | J57: 1200 | K57: 1200 | L57: UPI | M57: Pending | N57: Delivered | O57: 46229 | P57: 46228 | Q57: DTDC
A58: ORD057 | B58: 46295 | C58: C019 | D58: Prakash | E58: Salem | F58: P013 | G58: Bedsheet | H58: Home & Kitchen | I58: 4 | J58: 950 | K58: 3800 | L58: Net Banking | M58: Paid | N58: Confirmed | O58: 46299 | Q58: Delhivery
A59: ORD058 | B59: 46276 | C59: C004 | D59: Divya | E59: Trichy | F59: P010 | G59: Jeans | H59: Fashion | I59: 1 | J59: 1400 | K59: 1400 | L59: Net Banking | M59: Paid | N59: Returned | O59: 46279 | P59: 46279 | Q59: Ecom Express | R59: Product not as expected
A60: ORD059 | B60: 46205 | C60: C003 | D60: Rahul | E60: Coimbatore | F60: P017 | G60: Notebook | H60: Stationery | I60: 3 | J60: 180 | K60: 540 | L60: UPI | M60: Paid | N60: Delivered | O60: 46211 | P60: 46214 | Q60: Ecom Express
A61: ORD060 | B61: 46259 | C61: C012 | D61: Keerthana | E61: Salem | F61: P015 | G61: Cookware Set | H61: Home & Kitchen | I61: 2 | J61: 3200 | K61: 6400 | L61: Debit Card | M61: Pending | N61: Delivered | O61: 46263 | P61: 46265 | Q61: Ecom Express
A62: ORD061 | B62: 46245 | C62: C015 | D62: Santhosh | E62: Chennai | F62: P014 | G62: Water Bottle | H62: Home & Kitchen | I62: 3 | J62: 500 | K62: 1500 | L62: Debit Card | M62: Paid | N62: Delivered | O62: 46249 | P62: 46252 | Q62: Ecom Express
A63: ORD062 | B63: 46247 | C63: C008 | D63: Nisha | E63: Erode | F63: P015 | G63: Cookware Set | H63: Home & Kitchen | I63: 4 | J63: 3200 | K63: 12800 | L63: Credit Card | M63: Paid | N63: Delivered | O63: 46250 | P63: 46251 | Q63: Ecom Express
A64: ORD063 | B64: 46247 | C64: C007 | D64: Suresh | E64: Tenkasi | F64: P012 | G64: Sports Shoes | H64: Fashion | I64: 3 | J64: 2200 | K64: 6600 | L64: Debit Card | M64: Pending | N64: Confirmed | O64: 46252 | Q64: BlueDart
A65: ORD064 | B65: 46234 | C65: C017 | D65: Vijay | E65: Erode | F65: P007 | G65: Smart Watch | H65: Electronics | I65: 1 | J65: 2500 | K65: 2500 | L65: Net Banking | M65: Pending | N65: Cancelled | O65: 46240 | Q65: Delhivery | S65: Product unavailable
A66: ORD065 | B66: 46215 | C66: C016 | D66: Pavithra | E66: Madurai | F66: P015 | G66: Cookware Set | H66: Home & Kitchen | I66: 1 | J66: 3200 | K66: 3200 | L66: Cash on Delivery | M66: Paid | N66: Shipped | O66: 46220 | Q66: Delhivery
A67: ORD066 | B67: 46264 | C67: C010 | D67: Asha | E67: Madurai | F67: P019 | G67: Desk Organizer | H67: Stationery | I67: 3 | J67: 450 | K67: 1350 | L67: Cash on Delivery | M67: Paid | N67: Delivered | O67: 46271 | P67: 46272 | Q67: DTDC
A68: ORD067 | B68: 46243 | C68: C012 | D68: Keerthana | E68: Salem | F68: P015 | G68: Cookware Set | H68: Home & Kitchen | I68: 3 | J68: 3200 | K68: 9600 | L68: UPI | M68: Paid | N68: Shipped | O68: 46248 | Q68: Delhivery
A69: ORD068 | B69: 46228 | C69: C011 | D69: Manoj | E69: Coimbatore | F69: P004 | G69: Headphones | H69: Electronics | I69: 2 | J69: 1800 | K69: 3600 | L69: Debit Card | M69: Paid | N69: Delivered | O69: 46232 | P69: 46234 | Q69: DTDC
A70: ORD069 | B70: 46233 | C70: C004 | D70: Divya | E70: Trichy | F70: P007 | G70: Smart Watch | H70: Electronics | I70: 3 | J70: 2500 | K70: 7500 | L70: UPI | M70: Paid | N70: Delivered | O70: 46238 | P70: 46238 | Q70: Delhivery
A71: ORD070 | B71: 46274 | C71: C009 | D71: Vignesh | E71: Chennai | F71: P002 | G71: Keyboard | H71: Electronics | I71: 1 | J71: 850 | K71: 850 | L71: Credit Card | M71: Refunded | N71: Cancelled | O71: 46279 | Q71: Ecom Express | S71: Customer changed mind
A72: ORD071 | B72: 46264 | C72: C001 | D72: Arun Kumar | E72: Chennai | F72: P019 | G72: Desk Organizer | H72: Stationery | I72: 3 | J72: 450 | K72: 1350 | L72: Debit Card | M72: Paid | N72: Out for Delivery | O72: 46270 | Q72: Delhivery
A73: ORD072 | B73: 46218 | C73: C002 | D73: Priya | E73: Madurai | F73: P009 | G73: T-Shirt | H73: Fashion | I73: 4 | J73: 700 | K73: 2800 | L73: Cash on Delivery | M73: Pending | N73: Cancelled | O73: 46221 | Q73: BlueDart | S73: Delivery delay
A74: ORD073 | B74: 46276 | C74: C002 | D74: Priya | E74: Madurai | F74: P005 | G74: USB Cable | H74: Electronics | I74: 2 | J74: 350 | K74: 700 | L74: UPI | M74: Paid | N74: Delivered | O74: 46281 | P74: 46280 | Q74: Ecom Express
A75: ORD074 | B75: 46270 | C75: C020 | D75: Fathima | E75: Madurai | F75: P020 | G75: Calculator | H75: Stationery | I75: 2 | J75: 550 | K75: 1100 | L75: Debit Card | M75: Paid | N75: Delivered | O75: 46276 | P75: 46277 | Q75: Ecom Express
A76: ORD075 | B76: 46282 | C76: C010 | D76: Asha | E76: Madurai | F76: P019 | G76: Desk Organizer | H76: Stationery | I76: 1 | J76: 450 | K76: 450 | L76: Credit Card | M76: Paid | N76: Placed | O76: 46285 | Q76: DTDC
A77: ORD076 | B77: 46226 | C77: C003 | D77: Rahul | E77: Coimbatore | F77: P006 | G77: Power Bank | H77: Electronics | I77: 2 | J77: 1200 | K77: 2400 | L77: UPI | M77: Paid | N77: Delivered | O77: 46233 | P77: 46232 | Q77: Ecom Express
A78: ORD077 | B78: 46241 | C78: C015 | D78: Santhosh | E78: Chennai | F78: P020 | G78: Calculator | H78: Stationery | I78: 4 | J78: 550 | K78: 2200 | L78: Debit Card | M78: Paid | N78: Delivered | O78: 46244 | P78: 46244 | Q78: Ecom Express
A79: ORD078 | B79: 46284 | C79: C003 | D79: Rahul | E79: Coimbatore | F79: P008 | G79: Laptop Stand | H79: Electronics | I79: 3 | J79: 1100 | K79: 3300 | L79: Cash on Delivery | M79: Paid | N79: Delivered | O79: 46291 | P79: 46293 | Q79: BlueDart
A80: ORD079 | B80: 46238 | C80: C018 | D80: Harini | E80: Coimbatore | F80: P008 | G80: Laptop Stand | H80: Electronics | I80: 2 | J80: 1100 | K80: 2200 | L80: Credit Card | M80: Paid | N80: Delivered | O80: 46242 | P80: 46241 | Q80: DTDC
A81: ORD080 | B81: 46260 | C81: C020 | D81: Fathima | E81: Tirunelveli | F81: P019 | G81: Desk Organizer | H81: Stationery | I81: 3 | J81: 450 | K81: 1350 | L81: Debit Card | M81: Paid | N81: Returned | O81: 46263 | P81: 46264 | Q81: Ecom Express | R81: Product not as expected
A82: ORD081 | B82: 46260 | C82: C017 | D82: Vijay | E82: Erode | F82: P018 | G82: Office File | H82: Stationery | I82: 4 | J82: 120 | K82: 480 | L82: Cash on Delivery | M82: Paid | N82: Delivered | O82: 46263 | P82: 46264 | Q82: DTDC
A83: ORD082 | B83: 46215 | C83: C020 | D83: Fathima | E83: Tirunelveli | F83: P009 | G83: T-Shirt | H83: Fashion | I83: 1 | J83: 700 | K83: 700 | L83: Net Banking | M83: Pending | N83: Shipped | O83: 46219 | Q83: BlueDart
A84: ORD083 | B84: 46226 | C84: C009 | D84: Vignesh | E84: Chennai | F84: P019 | G84: Desk Organizer | H84: Stationery | I84: 1 | J84: 450 | K84: 450 | L84: Cash on Delivery | M84: Pending | N84: Delivered | O84: 46232 | P84: 46233 | Q84: DTDC
A85: ORD084 | B85: 46285 | C85: C006 | D85: Meena | E85: Tirunelveli | F85: P019 | G85: Desk Organizer | H85: Stationery | I85: 4 | J85: 450 | K85: 1800 | L85: Cash on Delivery | M85: Paid | N85: Shipped | O85: 46291 | Q85: DTDC
A86: ORD085 | B86: 46289 | C86: C014 | D86: Lavanya | E86: Tenkasi | F86: P011 | G86: Backpack | H86: Fashion | I86: 3 | J86: 1250 | K86: 3750 | L86: Debit Card | M86: Paid | N86: Out for Delivery | O86: 46292 | Q86: Ecom Express
A87: ORD086 | B87: 46274 | C87: C016 | D87: Pavithra | E87: Madurai | F87: P010 | G87: Jeans | H87: Fashion | I87: 4 | J87: 1400 | K87: 5600 | L87: Debit Card | M87: Paid | N87: Delivered | O87: 46277 | P87: 46278 | Q87: DTDC
A88: ORD087 | B88: 46269 | C88: C011 | D88: Manoj | E88: Coimbatore | F88: P004 | G88: Headphones | H88: Electronics | I88: 4 | J88: 1800 | K88: 7200 | L88: Cash on Delivery | M88: Pending | N88: Delivered | O88: 46272 | P88: 46274 | Q88: Ecom Express
A89: ORD088 | B89: 46283 | C89: C002 | D89: Priya | E89: Madurai | F89: P007 | G89: Smart Watch | H89: Electronics | I89: 3 | J89: 2500 | K89: 7500 | L89: Cash on Delivery | M89: Pending | N89: Out for Delivery | O89: 46289 | Q89: BlueDart
A90: ORD089 | B90: 46240 | C90: C007 | D90: Suresh | E90: Tenkasi | F90: P009 | G90: T-Shirt | H90: Fashion | I90: 2 | J90: 700 | K90: 1400 | L90: Cash on Delivery | M90: Pending | N90: Shipped | O90: 46246 | Q90: BlueDart
A91: ORD090 | B91: 46294 | C91: C001 | D91: Arun Kumar | E91: Chennai | F91: P020 | G91: Calculator | H91: Stationery | I91: 2 | J91: 550 | K91: 1100 | L91: Net Banking | M91: Pending | N91: Cancelled | O91: 46298 | Q91: BlueDart | S91: Delivery delay
A92: ORD091 | B92: 46218 | C92: C014 | D92: Lavanya | E92: Tenkasi | F92: P003 | G92: Bluetooth Speaker | H92: Electronics | I92: 2 | J92: 1450 | K92: 2900 | L92: Credit Card | M92: Pending | N92: Delivered | O92: 46224 | P92: 46223 | Q92: Ecom Express
A93: ORD092 | B93: 46257 | C93: C010 | D93: Asha | E93: Madurai | F93: P017 | G93: Notebook | H93: Stationery | I93: 3 | J93: 180 | K93: 540 | L93: Cash on Delivery | M93: Paid | N93: Delivered | O93: 46263 | P93: 46264 | Q93: Delhivery
A94: ORD093 | B94: 46212 | C94: C013 | D94: Dinesh | E94: Tirunelveli | F94: P007 | G94: Smart Watch | H94: Electronics | I94: 2 | J94: 2500 | K94: 5000 | L94: Debit Card | M94: Paid | N94: Out for Delivery | O94: 46217 | Q94: DTDC
A95: ORD094 | B95: 46279 | C95: C001 | D95: Arun Kumar | E95: Chennai | F95: P010 | G95: Jeans | H95: Fashion | I95: 3 | J95: 1400 | K95: 4200 | L95: Credit Card | M95: Paid | N95: Delivered | O95: 46286 | P95: 46288 | Q95: Ecom Express
A96: ORD095 | B96: 46246 | C96: C018 | D96: Harini | E96: Coimbatore | F96: P016 | G96: Storage Box | H96: Home & Kitchen | I96: 3 | J96: 750 | K96: 2250 | L96: Cash on Delivery | M96: Pending | N96: Confirmed | O96: 46253 | Q96: Ecom Express
A97: ORD096 | B97: 46277 | C97: C011 | D97: Manoj | E97: Coimbatore | F97: P007 | G97: Smart Watch | H97: Electronics | I97: 2 | J97: 2500 | K97: 5000 | L97: UPI | M97: Paid | N97: Delivered | O97: 46283 | P97: 46283 | Q97: DTDC
A98: ORD097 | B98: 46288 | C98: C016 | D98: Pavithra | E98: Madurai | F98: P013 | G98: Bedsheet | H98: Home & Kitchen | I98: 4 | J98: 950 | K98: 3800 | L98: Credit Card | M98: Paid | N98: Delivered | O98: 46292 | P98: 46293 | Q98: DTDC
A99: ORD098 | B99: 46271 | C99: C004 | D99: Divya | E99: Trichy | F99: P015 | G99: Cookware Set | H99: Home & Kitchen | I99: 1 | J99: 3200 | K99: 3200 | L99: Credit Card | M99: Failed | N99: Cancelled | O99: 46277 | Q99: Ecom Express | S99: Payment issue
A100: ORD099 | B100: 46247 | C100: C003 | D100: Rahul | E100: Coimbatore | F100: P016 | G100: Storage Box | H100: Home & Kitchen | I100: 3 | J100: 750 | K100: 2250 | L100: UPI | M100: Paid | N100: Delivered | O100: 46254 | P100: 46256 | Q100: DTDC
...

Sheet Cleaned_Data
A1: Order_ID | B1: Order_Date | C1: Customer_ID | D1: Customer_Name | E1: City | F1: Product_ID | G1: Product_Name | H1: Category | I1: Quantity | J1: Unit_Price | K1: Total_Amount | L1: Payment_Method | M1: Payment_Status | N1: Order_Status | O1: Expected_Delivery_Date | P1: Actual_Delivery_Date | Q1: Delivery_Partner | R1: Return_Reason | S1: Cancellation_Reason | T1: Delivery_Delay_Days | U1: Delivery_Performance | V1: Order Month
A2: ORD001 | B2: 46295 | C2: C007 | D2: Suresh | E2: Tenkasi | F2: P018 | G2: Office File | H2: Stationery | I2: 2 | J2: 120 | K2: 240 | L2: Debit Card | M2: Pending | N2: Delivered | O2: 46300 | P2: 46301 | Q2: Ecom Express | T2: =IF(P2="","",P2-O2) -> 1 | U2: =IF(T2="","Not Delivered",IF(T2<=0,"On Time",IF(T2<=2,"Slightly Delayed","Delayed"))) -> Slightly Delayed | V2: =TEXT(B2,"mmmm") -> September
A3: ORD002 | B3: 46235 | C3: C017 | D3: Vijay | E3: Erode | F3: P015 | G3: Cookware Set | H3: Home & Kitchen | I3: 1 | J3: 3200 | K3: 3200 | L3: Debit Card | M3: Failed | N3: Cancelled | O3: 46239 | Q3: BlueDart | S3: Delivery delay | T3: =IF(P3="","",P3-O3) | U3: =IF(T3="","Not Delivered",IF(T3<=0,"On Time",IF(T3<=2,"Slightly Delayed","Delayed"))) -> Not Delivered | V3: =TEXT(B3,"mmmm") -> August
A4: ORD003 | B4: 46204 | C4: C018 | D4: Harini | E4: Coimbatore | F4: P008 | G4: Laptop Stand | H4: Electronics | I4: 2 | J4: 1100 | K4: 2200 | L4: UPI | M4: Pending | N4: Delivered | O4: 46207 | P4: 46209 | Q4: Delhivery | T4: =IF(P4="","",P4-O4) -> 2 | U4: =IF(T4="","Not Delivered",IF(T4<=0,"On Time",IF(T4<=2,"Slightly Delayed","Delayed"))) -> Slightly Delayed | V4: =TEXT(B4,"mmmm") -> July
A5: ORD004 | B5: 46213 | C5: C003 | D5: Rahul | E5: Coimbatore | F5: P002 | G5: Keyboard | H5: Electronics | I5: 3 | J5: 850 | K5: 2550 | L5: Debit Card | M5: Paid | N5: Returned | O5: 46220 | P5: 46220 | Q5: Ecom Express | R5: Wrong product | T5: =IF(P5="","",P5-O5) -> 0 | U5: =IF(T5="","Not Delivered",IF(T5<=0,"On Time",IF(T5<=2,"Slightly Delayed","Delayed"))) -> On Time | V5: =TEXT(B5,"mmmm") -> July
A6: ORD005 | B6: 46235 | C6: C018 | D6: Harini | E6: Coimbatore | F6: P005 | G6: USB Cable | H6: Electronics | I6: 4 | J6: 350 | K6: 1400 | L6: Credit Card | M6: Paid | N6: Delivered | O6: 46241 | P6: 46244 | Q6: BlueDart | T6: =IF(P6="","",P6-O6) -> 3 | U6: =IF(T6="","Not Delivered",IF(T6<=0,"On Time",IF(T6<=2,"Slightly Delayed","Delayed"))) -> Delayed | V6: =TEXT(B6,"mmmm") -> August
A7: ORD006 | B7: 46258 | C7: C004 | D7: Divya | E7: Trichy | F7: P014 | G7: Water Bottle | H7: Home & Kitchen | I7: 3 | J7: 500 | K7: 1500 | L7: UPI | M7: Paid | N7: Shipped | O7: 46264 | Q7: BlueDart | T7: =IF(P7="","",P7-O7) | U7: =IF(T7="","Not Delivered",IF(T7<=0,"On Time",IF(T7<=2,"Slightly Delayed","Delayed"))) -> Not Delivered | V7: =TEXT(B7,"mmmm") -> August
A8: ORD007 | B8: 46217 | C8: C002 | D8: Priya | E8: Madurai | F8: P013 | G8: Bedsheet | H8: Home & Kitchen | I8: 3 | J8: 950 | K8: 2850 | L8: Net Banking | M8: Paid | N8: Delivered | O8: 46221 | P8: 46221 | Q8: Ecom Express | T8: =IF(P8="","",P8-O8) -> 0 | U8: =IF(T8="","Not Delivered",IF(T8<=0,"On Time",IF(T8<=2,"Slightly Delayed","Delayed"))) -> On Time | V8: =TEXT(B8,"mmmm") -> July
A9: ORD008 | B9: 46239 | C9: C005 | D9: Karthik | E9: Chennai | F9: P014 | G9: Water Bottle | H9: Home & Kitchen | I9: 2 | J9: 500 | K9: 1000 | L9: Cash on Delivery | M9: Paid | N9: Delivered | O9: 46245 | P9: 46245 | Q9: BlueDart | T9: =IF(P9="","",P9-O9) -> 0 | U9: =IF(T9="","Not Delivered",IF(T9<=0,"On Time",IF(T9<=2,"Slightly Delayed","Delayed"))) -> On Time | V9: =TEXT(B9,"mmmm") -> August
A10: ORD009 | B10: 46215 | C10: C002 | D10: Priya | E10: Madurai | F10: P018 | G10: Office File | H10: Stationery | I10: 1 | J10: 120 | K10: 120 | L10: Cash on Delivery | M10: Paid | N10: Delivered | O10: 46219 | P10: 46219 | Q10: Ecom Express | T10: =IF(P10="","",P10-O10) -> 0 | U10: =IF(T10="","Not Delivered",IF(T10<=0,"On Time",IF(T10<=2,"Slightly Delayed","Delayed"))) -> On Time | V10: =TEXT(B10,"mmmm") -> July
A11: ORD010 | B11: 46225 | C11: C007 | D11: Suresh | E11: Tenkasi | F11: P013 | G11: Bedsheet | H11: Home & Kitchen | I11: 1 | J11: 950 | K11: 950 | L11: Debit Card | M11: Paid | N11: Delivered | O11: 46231 | P11: 46230 | Q11: Ecom Express | T11: =IF(P11="","",P11-O11) -> -1 | U11: =IF(T11="","Not Delivered",IF(T11<=0,"On Time",IF(T11<=2,"Slightly Delayed","Delayed"))) -> On Time | V11: =TEXT(B11,"mmmm") -> July
A12: ORD011 | B12: 46223 | C12: C010 | D12: Asha | E12: Madurai | F12: P014 | G12: Water Bottle | H12: Home & Kitchen | I12: 4 | J12: 500 | K12: 2000 | L12: Credit Card | M12: Paid | N12: Shipped | O12: 46227 | Q12: BlueDart | T12: =IF(P12="","",P12-O12) | U12: =IF(T12="","Not Delivered",IF(T12<=0,"On Time",IF(T12<=2,"Slightly Delayed","Delayed"))) -> Not Delivered | V12: =TEXT(B12,"mmmm") -> July
A13: ORD012 | B13: 46244 | C13: C019 | D13: Prakash | E13: Salem | F13: P018 | G13: Office File | H13: Stationery | I13: 1 | J13: 120 | K13: 120 | L13: Net Banking | M13: Paid | N13: Placed | O13: 46247 | Q13: Ecom Express | T13: =IF(P13="","",P13-O13) | U13: =IF(T13="","Not Delivered",IF(T13<=0,"On Time",IF(T13<=2,"Slightly Delayed","Delayed"))) -> Not Delivered | V13: =TEXT(B13,"mmmm") -> August
A14: ORD013 | B14: 46211 | C14: C017 | D14: Vijay | E14: Erode | F14: P017 | G14: Notebook | H14: Stationery | I14: 2 | J14: 180 | K14: 360 | L14: Credit Card | M14: Paid | N14: Shipped | O14: 46218 | Q14: BlueDart | T14: =IF(P14="","",P14-O14) | U14: =IF(T14="","Not Delivered",IF(T14<=0,"On Time",IF(T14<=2,"Slightly Delayed","Delayed"))) -> Not Delivered | V14: =TEXT(B14,"mmmm") -> July
A15: ORD014 | B15: 46255 | C15: C020 | D15: Fathima | E15: Tirunelveli | F15: P003 | G15: Bluetooth Speaker | H15: Electronics | I15: 2 | J15: 1450 | K15: 2900 | L15: Net Banking | M15: Paid | N15: Delivered | O15: 46258 | P15: 46259 | Q15: BlueDart | T15: =IF(P15="","",P15-O15) -> 1 | U15: =IF(T15="","Not Delivered",IF(T15<=0,"On Time",IF(T15<=2,"Slightly Delayed","Delayed"))) -> Slightly Delayed | V15: =TEXT(B15,"mmmm") -> August
A16: ORD015 | B16: 46288 | C16: C020 | D16: Fathima | E16: Tirunelveli | F16: P003 | G16: Bluetooth Speaker | H16: Electronics | I16: 4 | J16: 1450 | K16: 5800 | L16: Net Banking | M16: Pending | N16: Confirmed | O16: 46295 | Q16: DTDC | T16: =IF(P16="","",P16-O16) | U16: =IF(T16="","Not Delivered",IF(T16<=0,"On Time",IF(T16<=2,"Slightly Delayed","Delayed"))) -> Not Delivered | V16: =TEXT(B16,"mmmm") -> September
A17: ORD016 | B17: 46234 | C17: C009 | D17: Vignesh | E17: Chennai | F17: P007 | G17: Smart Watch | H17: Electronics | I17: 3 | J17: 2500 | K17: 7500 | L17: Credit Card | M17: Paid | N17: Placed | O17: 46239 | Q17: DTDC | T17: =IF(P17="","",P17-O17) | U17: =IF(T17="","Not Delivered",IF(T17<=0,"On Time",IF(T17<=2,"Slightly Delayed","Delayed"))) -> Not Delivered | V17: =TEXT(B17,"mmmm") -> July
A18: ORD017 | B18: 46205 | C18: C015 | D18: Santhosh | E18: Chennai | F18: P011 | G18: Backpack | H18: Fashion | I18: 1 | J18: 1250 | K18: 1250 | L18: UPI | M18: Pending | N18: Delivered | O18: 46211 | P18: 46212 | Q18: BlueDart | T18: =IF(P18="","",P18-O18) -> 1 | U18: =IF(T18="","Not Delivered",IF(T18<=0,"On Time",IF(T18<=2,"Slightly Delayed","Delayed"))) -> Slightly Delayed | V18: =TEXT(B18,"mmmm") -> July
A19: ORD018 | B19: 46220 | C19: C018 | D19: Harini | E19: Coimbatore | F19: P007 | G19: Smart Watch | H19: Electronics | I19: 3 | J19: 2500 | K19: 7500 | L19: Credit Card | M19: Paid | N19: Shipped | O19: 46225 | Q19: DTDC | T19: =IF(P19="","",P19-O19) | U19: =IF(T19="","Not Delivered",IF(T19<=0,"On Time",IF(T19<=2,"Slightly Delayed","Delayed"))) -> Not Delivered | V19: =TEXT(B19,"mmmm") -> July
A20: ORD019 | B20: 46273 | C20: C010 | D20: Asha | E20: Madurai | F20: P006 | G20: Power Bank | H20: Electronics | I20: 4 | J20: 1200 | K20: 4800 | L20: Net Banking | M20: Pending | N20: Delivered | O20: 46278 | P20: 46279 | Q20: BlueDart | T20: =IF(P20="","",P20-O20) -> 1 | U20: =IF(T20="","Not Delivered",IF(T20<=0,"On Time",IF(T20<=2,"Slightly Delayed","Delayed"))) -> Slightly Delayed | V20: =TEXT(B20,"mmmm") -> September
A21: ORD020 | B21: 46221 | C21: C018 | D21: Harini | E21: Coimbatore | F21: P010 | G21: Jeans | H21: Fashion | I21: 1 | J21: 1400 | K21: 1400 | L21: Net Banking | M21: Paid | N21: Delivered | O21: 46226 | P21: 46225 | Q21: Delhivery | T21: =IF(P21="","",P21-O21) -> -1 | U21: =IF(T21="","Not Delivered",IF(T21<=0,"On Time",IF(T21<=2,"Slightly Delayed","Delayed"))) -> On Time | V21: =TEXT(B21,"mmmm") -> July
A22: ORD021 | B22: 46295 | C22: C009 | D22: Vignesh | E22: Chennai | F22: P010 | G22: Jeans | H22: Fashion | I22: 2 | J22: 1400 | K22: 2800 | L22: Debit Card | M22: Paid | N22: Confirmed | O22: 46300 | Q22: Ecom Express | T22: =IF(P22="","",P22-O22) | U22: =IF(T22="","Not Delivered",IF(T22<=0,"On Time",IF(T22<=2,"Slightly Delayed","Delayed"))) -> Not Delivered | V22: =TEXT(B22,"mmmm") -> September
A23: ORD022 | B23: 46285 | C23: C009 | D23: Vignesh | E23: Chennai | F23: P002 | G23: Keyboard | H23: Electronics | I23: 1 | J23: 850 | K23: 850 | L23: UPI | M23: Paid | N23: Delivered | O23: 46291 | P23: 46294 | Q23: BlueDart | T23: =IF(P23="","",P23-O23) -> 3 | U23: =IF(T23="","Not Delivered",IF(T23<=0,"On Time",IF(T23<=2,"Slightly Delayed","Delayed"))) -> Delayed | V23: =TEXT(B23,"mmmm") -> September
A24: ORD023 | B24: 46224 | C24: C011 | D24: Manoj | E24: Coimbatore | F24: P005 | G24: USB Cable | H24: Electronics | I24: 3 | J24: 350 | K24: 1050 | L24: Cash on Delivery | M24: Pending | N24: Delivered | O24: 46230 | P24: 46231 | Q24: BlueDart | T24: =IF(P24="","",P24-O24) -> 1 | U24: =IF(T24="","Not Delivered",IF(T24<=0,"On Time",IF(T24<=2,"Slightly Delayed","Delayed"))) -> Slightly Delayed | V24: =TEXT(B24,"mmmm") -> July
A25: ORD024 | B25: 46273 | C25: C004 | D25: Divya | E25: Trichy | F25: P003 | G25: Bluetooth Speaker | H25: Electronics | I25: 2 | J25: 1450 | K25: 2900 | L25: Net Banking | M25: Paid | N25: Shipped | O25: 46276 | Q25: Delhivery | T25: =IF(P25="","",P25-O25) | U25: =IF(T25="","Not Delivered",IF(T25<=0,"On Time",IF(T25<=2,"Slightly Delayed","Delayed"))) -> Not Delivered | V25: =TEXT(B25,"mmmm") -> September
A26: ORD025 | B26: 46243 | C26: C014 | D26: Lavanya | E26: Tenkasi | F26: P005 | G26: USB Cable | H26: Electronics | I26: 1 | J26: 350 | K26: 350 | L26: Debit Card | M26: Failed | N26: Cancelled | O26: 46248 | Q26: Delhivery | S26: Payment issue | T26: =IF(P26="","",P26-O26) | U26: =IF(T26="","Not Delivered",IF(T26<=0,"On Time",IF(T26<=2,"Slightly Delayed","Delayed"))) -> Not Delivered | V26: =TEXT(B26,"mmmm") -> August
A27: ORD026 | B27: 46283 | C27: C004 | D27: Divya | E27: Trichy | F27: P012 | G27: Sports Shoes | H27: Fashion | I27: 4 | J27: 2200 | K27: 8800 | L27: Credit Card | M27: Paid | N27: Confirmed | O27: 46287 | Q27: Delhivery | T27: =IF(P27="","",P27-O27) | U27: =IF(T27="","Not Delivered",IF(T27<=0,"On Time",IF(T27<=2,"Slightly Delayed","Delayed"))) -> Not Delivered | V27: =TEXT(B27,"mmmm") -> September
A28: ORD027 | B28: 46246 | C28: C014 | D28: Lavanya | E28: Tenkasi | F28: P001 | G28: Wireless Mouse | H28: Electronics | I28: 2 | J28: 650 | K28: 1300 | L28: Credit Card | M28: Pending | N28: Delivered | O28: 46252 | P28: 46255 | Q28: DTDC | T28: =IF(P28="","",P28-O28) -> 3 | U28: =IF(T28="","Not Delivered",IF(T28<=0,"On Time",IF(T28<=2,"Slightly Delayed","Delayed"))) -> Delayed | V28: =TEXT(B28,"mmmm") -> August
A29: ORD028 | B29: 46208 | C29: C006 | D29: Meena | E29: Tirunelveli | F29: P004 | G29: Headphones | H29: Electronics | I29: 4 | J29: 1800 | K29: 7200 | L29: Cash on Delivery | M29: Paid | N29: Delivered | O29: 46214 | P29: 46214 | Q29: DTDC | T29: =IF(P29="","",P29-O29) -> 0 | U29: =IF(T29="","Not Delivered",IF(T29<=0,"On Time",IF(T29<=2,"Slightly Delayed","Delayed"))) -> On Time | V29: =TEXT(B29,"mmmm") -> July
A30: ORD029 | B30: 46207 | C30: C010 | D30: Asha | E30: Madurai | F30: P008 | G30: Laptop Stand | H30: Electronics | I30: 2 | J30: 1100 | K30: 2200 | L30: Debit Card | M30: Paid | N30: Delivered | O30: 46211 | P30: 46212 | Q30: BlueDart | T30: =IF(P30="","",P30-O30) -> 1 | U30: =IF(T30="","Not Delivered",IF(T30<=0,"On Time",IF(T30<=2,"Slightly Delayed","Delayed"))) -> Slightly Delayed | V30: =TEXT(B30,"mmmm") -> July
A31: ORD030 | B31: 46290 | C31: C009 | D31: Vignesh | E31: Chennai | F31: P012 | G31: Sports Shoes | H31: Fashion | I31: 4 | J31: 2200 | K31: 8800 | L31: UPI | M31: Paid | N31: Returned | O31: 46297 | P31: 46297 | Q31: BlueDart | R31: Product not as expected | T31: =IF(P31="","",P31-O31) -> 0 | U31: =IF(T31="","Not Delivered",IF(T31<=0,"On Time",IF(T31<=2,"Slightly Delayed","Delayed"))) -> On Time | V31: =TEXT(B31,"mmmm") -> September
A32: ORD031 | B32: 46208 | C32: C006 | D32: Meena | E32: Tirunelveli | F32: P019 | G32: Desk Organizer | H32: Stationery | I32: 3 | J32: 450 | K32: 1350 | L32: Debit Card | M32: Paid | N32: Delivered | O32: 46211 | P32: 46212 | Q32: DTDC | T32: =IF(P32="","",P32-O32) -> 1 | U32: =IF(T32="","Not Delivered",IF(T32<=0,"On Time",IF(T32<=2,"Slightly Delayed","Delayed"))) -> Slightly Delayed | V32: =TEXT(B32,"mmmm") -> July
A33: ORD032 | B33: 46253 | C33: C014 | D33: Lavanya | E33: Tenkasi | F33: P020 | G33: Calculator | H33: Stationery | I33: 1 | J33: 550 | K33: 550 | L33: Debit Card | M33: Paid | N33: Shipped | O33: 46260 | Q33: BlueDart | T33: =IF(P33="","",P33-O33) | U33: =IF(T33="","Not Delivered",IF(T33<=0,"On Time",IF(T33<=2,"Slightly Delayed","Delayed"))) -> Not Delivered | V33: =TEXT(B33,"mmmm") -> August
A34: ORD033 | B34: 46250 | C34: C014 | D34: Lavanya | E34: Tenkasi | F34: P001 | G34: Wireless Mouse | H34: Electronics | I34: 2 | J34: 650 | K34: 1300 | L34: Debit Card | M34: Pending | N34: Delivered | O34: 46256 | P34: 46255 | Q34: DTDC | T34: =IF(P34="","",P34-O34) -> -1 | U34: =IF(T34="","Not Delivered",IF(T34<=0,"On Time",IF(T34<=2,"Slightly Delayed","Delayed"))) -> On Time | V34: =TEXT(B34,"mmmm") -> August
A35: ORD034 | B35: 46289 | C35: C004 | D35: Divya | E35: Trichy | F35: P010 | G35: Jeans | H35: Fashion | I35: 3 | J35: 1400 | K35: 4200 | L35: Debit Card | M35: Paid | N35: Delivered | O35: 46295 | P35: 46295 | Q35: Delhivery | T35: =IF(P35="","",P35-O35) -> 0 | U35: =IF(T35="","Not Delivered",IF(T35<=0,"On Time",IF(T35<=2,"Slightly Delayed","Delayed"))) -> On Time | V35: =TEXT(B35,"mmmm") -> September
A36: ORD035 | B36: 46290 | C36: C007 | D36: Suresh | E36: Tenkasi | F36: P014 | G36: Water Bottle | H36: Home & Kitchen | I36: 4 | J36: 500 | K36: 2000 | L36: Net Banking | M36: Pending | N36: Out for Delivery | O36: 46294 | Q36: DTDC | T36: =IF(P36="","",P36-O36) | U36: =IF(T36="","Not Delivered",IF(T36<=0,"On Time",IF(T36<=2,"Slightly Delayed","Delayed"))) -> Not Delivered | V36: =TEXT(B36,"mmmm") -> September
A37: ORD036 | B37: 46242 | C37: C013 | D37: Dinesh | E37: Tirunelveli | F37: P018 | G37: Office File | H37: Stationery | I37: 1 | J37: 120 | K37: 120 | L37: Net Banking | M37: Paid | N37: Delivered | O37: 46247 | P37: 46247 | Q37: DTDC | T37: =IF(P37="","",P37-O37) -> 0 | U37: =IF(T37="","Not Delivered",IF(T37<=0,"On Time",IF(T37<=2,"Slightly Delayed","Delayed"))) -> On Time | V37: =TEXT(B37,"mmmm") -> August
A38: ORD037 | B38: 46290 | C38: C015 | D38: Santhosh | E38: Chennai | F38: P015 | G38: Cookware Set | H38: Home & Kitchen | I38: 4 | J38: 3200 | K38: 12800 | L38: Credit Card | M38: Paid | N38: Delivered | O38: 46294 | P38: 46295 | Q38: BlueDart | T38: =IF(P38="","",P38-O38) -> 1 | U38: =IF(T38="","Not Delivered",IF(T38<=0,"On Time",IF(T38<=2,"Slightly Delayed","Delayed"))) -> Slightly Delayed | V38: =TEXT(B38,"mmmm") -> September
A39: ORD038 | B39: 46215 | C39: C010 | D39: Asha | E39: Madurai | F39: P017 | G39: Notebook | H39: Stationery | I39: 3 | J39: 180 | K39: 540 | L39: Debit Card | M39: Paid | N39: Returned | O39: 46219 | P39: 46221 | Q39: Delhivery | R39: Wrong product | T39: =IF(P39="","",P39-O39) -> 2 | U39: =IF(T39="","Not Delivered",IF(T39<=0,"On Time",IF(T39<=2,"Slightly Delayed","Delayed"))) -> Slightly Delayed | V39: =TEXT(B39,"mmmm") -> July
A40: ORD039 | B40: 46235 | C40: C005 | D40: Karthik | E40: Salem | F40: P001 | G40: Wireless Mouse | H40: Electronics | I40: 1 | J40: 650 | K40: 650 | L40: Cash on Delivery | M40: Paid | N40: Delivered | O40: 46241 | P40: 46242 | Q40: Ecom Express | T40: =IF(P40="","",P40-O40) -> 1 | U40: =IF(T40="","Not Delivered",IF(T40<=0,"On Time",IF(T40<=2,"Slightly Delayed","Delayed"))) -> Slightly Delayed | V40: =TEXT(B40,"mmmm") -> August
A41: ORD040 | B41: 46267 | C41: C019 | D41: Prakash | E41: Salem | F41: P007 | G41: Smart Watch | H41: Electronics | I41: 4 | J41: 2500 | K41: 10000 | L41: Credit Card | M41: Paid | N41: Placed | O41: 46273 | Q41: BlueDart | T41: =IF(P41="","",P41-O41) | U41: =IF(T41="","Not Delivered",IF(T41<=0,"On Time",IF(T41<=2,"Slightly Delayed","Delayed"))) -> Not Delivered | V41: =TEXT(B41,"mmmm") -> September
A42: ORD041 | B42: 46226 | C42: C004 | D42: Divya | E42: Trichy | F42: P014 | G42: Water Bottle | H42: Home & Kitchen | I42: 2 | J42: 500 | K42: 1000 | L42: UPI | M42: Paid | N42: Placed | O42: 46233 | Q42: Delhivery | T42: =IF(P42="","",P42-O42) | U42: =IF(T42="","Not Delivered",IF(T42<=0,"On Time",IF(T42<=2,"Slightly Delayed","Delayed"))) -> Not Delivered | V42: =TEXT(B42,"mmmm") -> July
A43: ORD042 | B43: 46263 | C43: C004 | D43: Divya | E43: Trichy | F43: P015 | G43: Cookware Set | H43: Home & Kitchen | I43: 2 | J43: 3200 | K43: 6400 | L43: Debit Card | M43: Pending | N43: Delivered | O43: 46270 | P43: 46271 | Q43: Ecom Express | T43: =IF(P43="","",P43-O43) -> 1 | U43: =IF(T43="","Not Delivered",IF(T43<=0,"On Time",IF(T43<=2,"Slightly Delayed","Delayed"))) -> Slightly Delayed | V43: =TEXT(B43,"mmmm") -> August
A44: ORD043 | B44: 46274 | C44: C020 | D44: Fathima | E44: Tirunelveli | F44: P017 | G44: Notebook | H44: Stationery | I44: 4 | J44: 180 | K44: 720 | L44: Cash on Delivery | M44: Pending | N44: Delivered | O44: 46280 | P44: 46280 | Q44: Ecom Express | T44: =IF(P44="","",P44-O44) -> 0 | U44: =IF(T44="","Not Delivered",IF(T44<=0,"On Time",IF(T44<=2,"Slightly Delayed","Delayed"))) -> On Time | V44: =TEXT(B44,"mmmm") -> September
A45: ORD044 | B45: 46270 | C45: C009 | D45: Vignesh | E45: Chennai | F45: P008 | G45: Laptop Stand | H45: Electronics | I45: 3 | J45: 1100 | K45: 3300 | L45: Credit Card | M45: Pending | N45: Out for Delivery | O45: 46276 | Q45: DTDC | T45: =IF(P45="","",P45-O45) | U45: =IF(T45="","Not Delivered",IF(T45<=0,"On Time",IF(T45<=2,"Slightly Delayed","Delayed"))) -> Not Delivered | V45: =TEXT(B45,"mmmm") -> September
A46: ORD045 | B46: 46234 | C46: C015 | D46: Santhosh | E46: Chennai | F46: P003 | G46: Bluetooth Speaker | H46: Electronics | I46: 3 | J46: 1450 | K46: 4350 | L46: UPI | M46: Paid | N46: Confirmed | O46: 46239 | Q46: BlueDart | T46: =IF(P46="","",P46-O46) | U46: =IF(T46="","Not Delivered",IF(T46<=0,"On Time",IF(T46<=2,"Slightly Delayed","Delayed"))) -> Not Delivered | V46: =TEXT(B46,"mmmm") -> July
A47: ORD046 | B47: 46253 | C47: C005 | D47: Karthik | E47: Salem | F47: P005 | G47: USB Cable | H47: Electronics | I47: 2 | J47: 350 | K47: 700 | L47: UPI | M47: Paid | N47: Delivered | O47: 46257 | P47: 46259 | Q47: Ecom Express | T47: =IF(P47="","",P47-O47) -> 2 | U47: =IF(T47="","Not Delivered",IF(T47<=0,"On Time",IF(T47<=2,"Slightly Delayed","Delayed"))) -> Slightly Delayed | V47: =TEXT(B47,"mmmm") -> August
A48: ORD047 | B48: 46257 | C48: C014 | D48: Lavanya | E48: Tenkasi | F48: P011 | G48: Backpack | H48: Fashion | I48: 4 | J48: 1250 | K48: 5000 | L48: Cash on Delivery | M48: Paid | N48: Shipped | O48: 46260 | Q48: Ecom Express | T48: =IF(P48="","",P48-O48) | U48: =IF(T48="","Not Delivered",IF(T48<=0,"On Time",IF(T48<=2,"Slightly Delayed","Delayed"))) -> Not Delivered | V48: =TEXT(B48,"mmmm") -> August
A49: ORD048 | B49: 46265 | C49: C019 | D49: Prakash | E49: Salem | F49: P001 | G49: Wireless Mouse | H49: Electronics | I49: 4 | J49: 650 | K49: 2600 | L49: Cash on Delivery | M49: Paid | N49: Delivered | O49: 46268 | P49: 46268 | Q49: Ecom Express | T49: =IF(P49="","",P49-O49) -> 0 | U49: =IF(T49="","Not Delivered",IF(T49<=0,"On Time",IF(T49<=2,"Slightly Delayed","Delayed"))) -> On Time | V49: =TEXT(B49,"mmmm") -> August
A50: ORD049 | B50: 46266 | C50: C018 | D50: Harini | E50: Coimbatore | F50: P018 | G50: Office File | H50: Stationery | I50: 2 | J50: 120 | K50: 240 | L50: Cash on Delivery | M50: Paid | N50: Delivered | O50: 46270 | P50: 46270 | Q50: BlueDart | T50: =IF(P50="","",P50-O50) -> 0 | U50: =IF(T50="","Not Delivered",IF(T50<=0,"On Time",IF(T50<=2,"Slightly Delayed","Delayed"))) -> On Time | V50: =TEXT(B50,"mmmm") -> September
A51: ORD050 | B51: 46225 | C51: C013 | D51: Dinesh | E51: Tirunelveli | F51: P011 | G51: Backpack | H51: Fashion | I51: 4 | J51: 1250 | K51: 5000 | L51: Net Banking | M51: Pending | N51: Delivered | O51: 46231 | P51: 46231 | Q51: BlueDart | T51: =IF(P51="","",P51-O51) -> 0 | U51: =IF(T51="","Not Delivered",IF(T51<=0,"On Time",IF(T51<=2,"Slightly Delayed","Delayed"))) -> On Time | V51: =TEXT(B51,"mmmm") -> July
A52: ORD051 | B52: 46214 | C52: C013 | D52: Dinesh | E52: Tirunelveli | F52: P019 | G52: Desk Organizer | H52: Stationery | I52: 1 | J52: 450 | K52: 450 | L52: Credit Card | M52: Paid | N52: Delivered | O52: 46220 | P52: 46220 | Q52: BlueDart | T52: =IF(P52="","",P52-O52) -> 0 | U52: =IF(T52="","Not Delivered",IF(T52<=0,"On Time",IF(T52<=2,"Slightly Delayed","Delayed"))) -> On Time | V52: =TEXT(B52,"mmmm") -> July
A53: ORD052 | B53: 46231 | C53: C009 | D53: Vignesh | E53: Chennai | F53: P013 | G53: Bedsheet | H53: Home & Kitchen | I53: 3 | J53: 950 | K53: 2850 | L53: Cash on Delivery | M53: Paid | N53: Delivered | O53: 46237 | P53: 46237 | Q53: DTDC | T53: =IF(P53="","",P53-O53) -> 0 | U53: =IF(T53="","Not Delivered",IF(T53<=0,"On Time",IF(T53<=2,"Slightly Delayed","Delayed"))) -> On Time | V53: =TEXT(B53,"mmmm") -> July
A54: ORD053 | B54: 46264 | C54: C014 | D54: Lavanya | E54: Tenkasi | F54: P009 | G54: T-Shirt | H54: Fashion | I54: 1 | J54: 700 | K54: 700 | L54: UPI | M54: Pending | N54: Delivered | O54: 46267 | P54: 46269 | Q54: DTDC | T54: =IF(P54="","",P54-O54) -> 2 | U54: =IF(T54="","Not Delivered",IF(T54<=0,"On Time",IF(T54<=2,"Slightly Delayed","Delayed"))) -> Slightly Delayed | V54: =TEXT(B54,"mmmm") -> August
A55: ORD054 | B55: 46207 | C55: C008 | D55: Nisha | E55: Erode | F55: P003 | G55: Bluetooth Speaker | H55: Electronics | I55: 1 | J55: 1450 | K55: 1450 | L55: UPI | M55: Paid | N55: Out for Delivery | O55: 46211 | Q55: Delhivery | T55: =IF(P55="","",P55-O55) | U55: =IF(T55="","Not Delivered",IF(T55<=0,"On Time",IF(T55<=2,"Slightly Delayed","Delayed"))) -> Not Delivered | V55: =TEXT(B55,"mmmm") -> July
A56: ORD055 | B56: 46289 | C56: C008 | D56: Nisha | E56: Erode | F56: P005 | G56: USB Cable | H56: Electronics | I56: 4 | J56: 350 | K56: 1400 | L56: Cash on Delivery | M56: Paid | N56: Delivered | O56: 46292 | P56: 46293 | Q56: DTDC | T56: =IF(P56="","",P56-O56) -> 1 | U56: =IF(T56="","Not Delivered",IF(T56<=0,"On Time",IF(T56<=2,"Slightly Delayed","Delayed"))) -> Slightly Delayed | V56: =TEXT(B56,"mmmm") -> September
A57: ORD056 | B57: 46224 | C57: C012 | D57: Keerthana | E57: Salem | F57: P006 | G57: Power Bank | H57: Electronics | I57: 1 | J57: 1200 | K57: 1200 | L57: UPI | M57: Pending | N57: Delivered | O57: 46229 | P57: 46228 | Q57: DTDC | T57: =IF(P57="","",P57-O57) -> -1 | U57: =IF(T57="","Not Delivered",IF(T57<=0,"On Time",IF(T57<=2,"Slightly Delayed","Delayed"))) -> On Time | V57: =TEXT(B57,"mmmm") -> July
A58: ORD057 | B58: 46295 | C58: C019 | D58: Prakash | E58: Salem | F58: P013 | G58: Bedsheet | H58: Home & Kitchen | I58: 4 | J58: 950 | K58: 3800 | L58: Net Banking | M58: Paid | N58: Confirmed | O58: 46299 | Q58: Delhivery | T58: =IF(P58="","",P58-O58) | U58: =IF(T58="","Not Delivered",IF(T58<=0,"On Time",IF(T58<=2,"Slightly Delayed","Delayed"))) -> Not Delivered | V58: =TEXT(B58,"mmmm") -> September
A59: ORD058 | B59: 46276 | C59: C004 | D59: Divya | E59: Trichy | F59: P010 | G59: Jeans | H59: Fashion | I59: 1 | J59: 1400 | K59: 1400 | L59: Net Banking | M59: Paid | N59: Returned | O59: 46279 | P59: 46279 | Q59: Ecom Express | R59: Product not as expected | T59: =IF(P59="","",P59-O59) -> 0 | U59: =IF(T59="","Not Delivered",IF(T59<=0,"On Time",IF(T59<=2,"Slightly Delayed","Delayed"))) -> On Time | V59: =TEXT(B59,"mmmm") -> September
A60: ORD059 | B60: 46205 | C60: C003 | D60: Rahul | E60: Coimbatore | F60: P017 | G60: Notebook | H60: Stationery | I60: 3 | J60: 180 | K60: 540 | L60: UPI | M60: Paid | N60: Delivered | O60: 46211 | P60: 46214 | Q60: Ecom Express | T60: =IF(P60="","",P60-O60) -> 3 | U60: =IF(T60="","Not Delivered",IF(T60<=0,"On Time",IF(T60<=2,"Slightly Delayed","Delayed"))) -> Delayed | V60: =TEXT(B60,"mmmm") -> July
A61: ORD060 | B61: 46259 | C61: C012 | D61: Keerthana | E61: Salem | F61: P015 | G61: Cookware Set | H61: Home & Kitchen | I61: 2 | J61: 3200 | K61: 6400 | L61: Debit Card | M61: Pending | N61: Delivered | O61: 46263 | P61: 46265 | Q61: Ecom Express | T61: =IF(P61="","",P61-O61) -> 2 | U61: =IF(T61="","Not Delivered",IF(T61<=0,"On Time",IF(T61<=2,"Slightly Delayed","Delayed"))) -> Slightly Delayed | V61: =TEXT(B61,"mmmm") -> August
A62: ORD061 | B62: 46245 | C62: C015 | D62: Santhosh | E62: Chennai | F62: P014 | G62: Water Bottle | H62: Home & Kitchen | I62: 3 | J62: 500 | K62: 1500 | L62: Debit Card | M62: Paid | N62: Delivered | O62: 46249 | P62: 46252 | Q62: Ecom Express | T62: =IF(P62="","",P62-O62) -> 3 | U62: =IF(T62="","Not Delivered",IF(T62<=0,"On Time",IF(T62<=2,"Slightly Delayed","Delayed"))) -> Delayed | V62: =TEXT(B62,"mmmm") -> August
A63: ORD062 | B63: 46247 | C63: C008 | D63: Nisha | E63: Erode | F63: P015 | G63: Cookware Set | H63: Home & Kitchen | I63: 4 | J63: 3200 | K63: 12800 | L63: Credit Card | M63: Paid | N63: Delivered | O63: 46250 | P63: 46251 | Q63: Ecom Express | T63: =IF(P63="","",P63-O63) -> 1 | U63: =IF(T63="","Not Delivered",IF(T63<=0,"On Time",IF(T63<=2,"Slightly Delayed","Delayed"))) -> Slightly Delayed | V63: =TEXT(B63,"mmmm") -> August
A64: ORD063 | B64: 46247 | C64: C007 | D64: Suresh | E64: Tenkasi | F64: P012 | G64: Sports Shoes | H64: Fashion | I64: 3 | J64: 2200 | K64: 6600 | L64: Debit Card | M64: Pending | N64: Confirmed | O64: 46252 | Q64: BlueDart | T64: =IF(P64="","",P64-O64) | U64: =IF(T64="","Not Delivered",IF(T64<=0,"On Time",IF(T64<=2,"Slightly Delayed","Delayed"))) -> Not Delivered | V64: =TEXT(B64,"mmmm") -> August
A65: ORD064 | B65: 46234 | C65: C017 | D65: Vijay | E65: Erode | F65: P007 | G65: Smart Watch | H65: Electronics | I65: 1 | J65: 2500 | K65: 2500 | L65: Net Banking | M65: Pending | N65: Cancelled | O65: 46240 | Q65: Delhivery | S65: Product unavailable | T65: =IF(P65="","",P65-O65) | U65: =IF(T65="","Not Delivered",IF(T65<=0,"On Time",IF(T65<=2,"Slightly Delayed","Delayed"))) -> Not Delivered | V65: =TEXT(B65,"mmmm") -> July
A66: ORD065 | B66: 46215 | C66: C016 | D66: Pavithra | E66: Madurai | F66: P015 | G66: Cookware Set | H66: Home & Kitchen | I66: 1 | J66: 3200 | K66: 3200 | L66: Cash on Delivery | M66: Paid | N66: Shipped | O66: 46220 | Q66: Delhivery | T66: =IF(P66="","",P66-O66) | U66: =IF(T66="","Not Delivered",IF(T66<=0,"On Time",IF(T66<=2,"Slightly Delayed","Delayed"))) -> Not Delivered | V66: =TEXT(B66,"mmmm") -> July
A67: ORD066 | B67: 46264 | C67: C010 | D67: Asha | E67: Madurai | F67: P019 | G67: Desk Organizer | H67: Stationery | I67: 3 | J67: 450 | K67: 1350 | L67: Cash on Delivery | M67: Paid | N67: Delivered | O67: 46271 | P67: 46272 | Q67: DTDC | T67: =IF(P67="","",P67-O67) -> 1 | U67: =IF(T67="","Not Delivered",IF(T67<=0,"On Time",IF(T67<=2,"Slightly Delayed","Delayed"))) -> Slightly Delayed | V67: =TEXT(B67,"mmmm") -> August
A68: ORD067 | B68: 46243 | C68: C012 | D68: Keerthana | E68: Salem | F68: P015 | G68: Cookware Set | H68: Home & Kitchen | I68: 3 | J68: 3200 | K68: 9600 | L68: UPI | M68: Paid | N68: Shipped | O68: 46248 | Q68: Delhivery | T68: =IF(P68="","",P68-O68) | U68: =IF(T68="","Not Delivered",IF(T68<=0,"On Time",IF(T68<=2,"Slightly Delayed","Delayed"))) -> Not Delivered | V68: =TEXT(B68,"mmmm") -> August
A69: ORD068 | B69: 46228 | C69: C011 | D69: Manoj | E69: Coimbatore | F69: P004 | G69: Headphones | H69: Electronics | I69: 2 | J69: 1800 | K69: 3600 | L69: Debit Card | M69: Paid | N69: Delivered | O69: 46232 | P69: 46234 | Q69: DTDC | T69: =IF(P69="","",P69-O69) -> 2 | U69: =IF(T69="","Not Delivered",IF(T69<=0,"On Time",IF(T69<=2,"Slightly Delayed","Delayed"))) -> Slightly Delayed | V69: =TEXT(B69,"mmmm") -> July
A70: ORD069 | B70: 46233 | C70: C004 | D70: Divya | E70: Trichy | F70: P007 | G70: Smart Watch | H70: Electronics | I70: 3 | J70: 2500 | K70: 7500 | L70: UPI | M70: Paid | N70: Delivered | O70: 46238 | P70: 46238 | Q70: Delhivery | T70: =IF(P70="","",P70-O70) -> 0 | U70: =IF(T70="","Not Delivered",IF(T70<=0,"On Time",IF(T70<=2,"Slightly Delayed","Delayed"))) -> On Time | V70: =TEXT(B70,"mmmm") -> July
A71: ORD070 | B71: 46274 | C71: C009 | D71: Vignesh | E71: Chennai | F71: P002 | G71: Keyboard | H71: Electronics | I71: 1 | J71: 850 | K71: 850 | L71: Credit Card | M71: Refunded | N71: Cancelled | O71: 46279 | Q71: Ecom Express | S71: Customer changed mind | T71: =IF(P71="","",P71-O71) | U71: =IF(T71="","Not Delivered",IF(T71<=0,"On Time",IF(T71<=2,"Slightly Delayed","Delayed"))) -> Not Delivered | V71: =TEXT(B71,"mmmm") -> September
A72: ORD071 | B72: 46264 | C72: C001 | D72: Arun Kumar | E72: Chennai | F72: P019 | G72: Desk Organizer | H72: Stationery | I72: 3 | J72: 450 | K72: 1350 | L72: Debit Card | M72: Paid | N72: Out for Delivery | O72: 46270 | Q72: Delhivery | T72: =IF(P72="","",P72-O72) | U72: =IF(T72="","Not Delivered",IF(T72<=0,"On Time",IF(T72<=2,"Slightly Delayed","Delayed"))) -> Not Delivered | V72: =TEXT(B72,"mmmm") -> August
A73: ORD072 | B73: 46218 | C73: C002 | D73: Priya | E73: Madurai | F73: P009 | G73: T-Shirt | H73: Fashion | I73: 4 | J73: 700 | K73: 2800 | L73: Cash on Delivery | M73: Pending | N73: Cancelled | O73: 46221 | Q73: BlueDart | S73: Delivery delay | T73: =IF(P73="","",P73-O73) | U73: =IF(T73="","Not Delivered",IF(T73<=0,"On Time",IF(T73<=2,"Slightly Delayed","Delayed"))) -> Not Delivered | V73: =TEXT(B73,"mmmm") -> July
A74: ORD073 | B74: 46276 | C74: C002 | D74: Priya | E74: Madurai | F74: P005 | G74: USB Cable | H74: Electronics | I74: 2 | J74: 350 | K74: 700 | L74: UPI | M74: Paid | N74: Delivered | O74: 46281 | P74: 46280 | Q74: Ecom Express | T74: =IF(P74="","",P74-O74) -> -1 | U74: =IF(T74="","Not Delivered",IF(T74<=0,"On Time",IF(T74<=2,"Slightly Delayed","Delayed"))) -> On Time | V74: =TEXT(B74,"mmmm") -> September
A75: ORD074 | B75: 46270 | C75: C020 | D75: Fathima | E75: Madurai | F75: P020 | G75: Calculator | H75: Stationery | I75: 2 | J75: 550 | K75: 1100 | L75: Debit Card | M75: Paid | N75: Delivered | O75: 46276 | P75: 46277 | Q75: Ecom Express | T75: =IF(P75="","",P75-O75) -> 1 | U75: =IF(T75="","Not Delivered",IF(T75<=0,"On Time",IF(T75<=2,"Slightly Delayed","Delayed"))) -> Slightly Delayed | V75: =TEXT(B75,"mmmm") -> September
A76: ORD075 | B76: 46282 | C76: C010 | D76: Asha | E76: Madurai | F76: P019 | G76: Desk Organizer | H76: Stationery | I76: 1 | J76: 450 | K76: 450 | L76: Credit Card | M76: Paid | N76: Placed | O76: 46285 | Q76: DTDC | T76: =IF(P76="","",P76-O76) | U76: =IF(T76="","Not Delivered",IF(T76<=0,"On Time",IF(T76<=2,"Slightly Delayed","Delayed"))) -> Not Delivered | V76: =TEXT(B76,"mmmm") -> September
A77: ORD076 | B77: 46226 | C77: C003 | D77: Rahul | E77: Coimbatore | F77: P006 | G77: Power Bank | H77: Electronics | I77: 2 | J77: 1200 | K77: 2400 | L77: UPI | M77: Paid | N77: Delivered | O77: 46233 | P77: 46232 | Q77: Ecom Express | T77: =IF(P77="","",P77-O77) -> -1 | U77: =IF(T77="","Not Delivered",IF(T77<=0,"On Time",IF(T77<=2,"Slightly Delayed","Delayed"))) -> On Time | V77: =TEXT(B77,"mmmm") -> July
A78: ORD077 | B78: 46241 | C78: C015 | D78: Santhosh | E78: Chennai | F78: P020 | G78: Calculator | H78: Stationery | I78: 4 | J78: 550 | K78: 2200 | L78: Debit Card | M78: Paid | N78: Delivered | O78: 46244 | P78: 46244 | Q78: Ecom Express | T78: =IF(P78="","",P78-O78) -> 0 | U78: =IF(T78="","Not Delivered",IF(T78<=0,"On Time",IF(T78<=2,"Slightly Delayed","Delayed"))) -> On Time | V78: =TEXT(B78,"mmmm") -> August
A79: ORD078 | B79: 46284 | C79: C003 | D79: Rahul | E79: Coimbatore | F79: P008 | G79: Laptop Stand | H79: Electronics | I79: 3 | J79: 1100 | K79: 3300 | L79: Cash on Delivery | M79: Paid | N79: Delivered | O79: 46291 | P79: 46293 | Q79: BlueDart | T79: =IF(P79="","",P79-O79) -> 2 | U79: =IF(T79="","Not Delivered",IF(T79<=0,"On Time",IF(T79<=2,"Slightly Delayed","Delayed"))) -> Slightly Delayed | V79: =TEXT(B79,"mmmm") -> September
A80: ORD079 | B80: 46238 | C80: C018 | D80: Harini | E80: Coimbatore | F80: P008 | G80: Laptop Stand | H80: Electronics | I80: 2 | J80: 1100 | K80: 2200 | L80: Credit Card | M80: Paid | N80: Delivered | O80: 46242 | P80: 46241 | Q80: DTDC | T80: =IF(P80="","",P80-O80) -> -1 | U80: =IF(T80="","Not Delivered",IF(T80<=0,"On Time",IF(T80<=2,"Slightly Delayed","Delayed"))) -> On Time | V80: =TEXT(B80,"mmmm") -> August
A81: ORD080 | B81: 46260 | C81: C020 | D81: Fathima | E81: Tirunelveli | F81: P019 | G81: Desk Organizer | H81: Stationery | I81: 3 | J81: 450 | K81: 1350 | L81: Debit Card | M81: Paid | N81: Returned | O81: 46263 | P81: 46264 | Q81: Ecom Express | R81: Product not as expected | T81: =IF(P81="","",P81-O81) -> 1 | U81: =IF(T81="","Not Delivered",IF(T81<=0,"On Time",IF(T81<=2,"Slightly Delayed","Delayed"))) -> Slightly Delayed | V81: =TEXT(B81,"mmmm") -> August
A82: ORD081 | B82: 46260 | C82: C017 | D82: Vijay | E82: Erode | F82: P018 | G82: Office File | H82: Stationery | I82: 4 | J82: 120 | K82: 480 | L82: Cash on Delivery | M82: Paid | N82: Delivered | O82: 46263 | P82: 46264 | Q82: DTDC | T82: =IF(P82="","",P82-O82) -> 1 | U82: =IF(T82="","Not Delivered",IF(T82<=0,"On Time",IF(T82<=2,"Slightly Delayed","Delayed"))) -> Slightly Delayed | V82: =TEXT(B82,"mmmm") -> August
A83: ORD082 | B83: 46215 | C83: C020 | D83: Fathima | E83: Tirunelveli | F83: P009 | G83: T-Shirt | H83: Fashion | I83: 1 | J83: 700 | K83: 700 | L83: Net Banking | M83: Pending | N83: Shipped | O83: 46219 | Q83: BlueDart | T83: =IF(P83="","",P83-O83) | U83: =IF(T83="","Not Delivered",IF(T83<=0,"On Time",IF(T83<=2,"Slightly Delayed","Delayed"))) -> Not Delivered | V83: =TEXT(B83,"mmmm") -> July
A84: ORD083 | B84: 46226 | C84: C009 | D84: Vignesh | E84: Chennai | F84: P019 | G84: Desk Organizer | H84: Stationery | I84: 1 | J84: 450 | K84: 450 | L84: Cash on Delivery | M84: Pending | N84: Delivered | O84: 46232 | P84: 46233 | Q84: DTDC | T84: =IF(P84="","",P84-O84) -> 1 | U84: =IF(T84="","Not Delivered",IF(T84<=0,"On Time",IF(T84<=2,"Slightly Delayed","Delayed"))) -> Slightly Delayed | V84: =TEXT(B84,"mmmm") -> July
A85: ORD084 | B85: 46285 | C85: C006 | D85: Meena | E85: Tirunelveli | F85: P019 | G85: Desk Organizer | H85: Stationery | I85: 4 | J85: 450 | K85: 1800 | L85: Cash on Delivery | M85: Paid | N85: Shipped | O85: 46291 | Q85: DTDC | T85: =IF(P85="","",P85-O85) | U85: =IF(T85="","Not Delivered",IF(T85<=0,"On Time",IF(T85<=2,"Slightly Delayed","Delayed"))) -> Not Delivered | V85: =TEXT(B85,"mmmm") -> September
A86: ORD085 | B86: 46289 | C86: C014 | D86: Lavanya | E86: Tenkasi | F86: P011 | G86: Backpack | H86: Fashion | I86: 3 | J86: 1250 | K86: 3750 | L86: Debit Card | M86: Paid | N86: Out for Delivery | O86: 46292 | Q86: Ecom Express | T86: =IF(P86="","",P86-O86) | U86: =IF(T86="","Not Delivered",IF(T86<=0,"On Time",IF(T86<=2,"Slightly Delayed","Delayed"))) -> Not Delivered | V86: =TEXT(B86,"mmmm") -> September
A87: ORD086 | B87: 46274 | C87: C016 | D87: Pavithra | E87: Madurai | F87: P010 | G87: Jeans | H87: Fashion | I87: 4 | J87: 1400 | K87: 5600 | L87: Debit Card | M87: Paid | N87: Delivered | O87: 46277 | P87: 46278 | Q87: DTDC | T87: =IF(P87="","",P87-O87) -> 1 | U87: =IF(T87="","Not Delivered",IF(T87<=0,"On Time",IF(T87<=2,"Slightly Delayed","Delayed"))) -> Slightly Delayed | V87: =TEXT(B87,"mmmm") -> September
A88: ORD087 | B88: 46269 | C88: C011 | D88: Manoj | E88: Coimbatore | F88: P004 | G88: Headphones | H88: Electronics | I88: 4 | J88: 1800 | K88: 7200 | L88: Cash on Delivery | M88: Pending | N88: Delivered | O88: 46272 | P88: 46274 | Q88: Ecom Express | T88: =IF(P88="","",P88-O88) -> 2 | U88: =IF(T88="","Not Delivered",IF(T88<=0,"On Time",IF(T88<=2,"Slightly Delayed","Delayed"))) -> Slightly Delayed | V88: =TEXT(B88,"mmmm") -> September
A89: ORD088 | B89: 46283 | C89: C002 | D89: Priya | E89: Madurai | F89: P007 | G89: Smart Watch | H89: Electronics | I89: 3 | J89: 2500 | K89: 7500 | L89: Cash on Delivery | M89: Pending | N89: Out for Delivery | O89: 46289 | Q89: BlueDart | T89: =IF(P89="","",P89-O89) | U89: =IF(T89="","Not Delivered",IF(T89<=0,"On Time",IF(T89<=2,"Slightly Delayed","Delayed"))) -> Not Delivered | V89: =TEXT(B89,"mmmm") -> September
A90: ORD089 | B90: 46240 | C90: C007 | D90: Suresh | E90: Tenkasi | F90: P009 | G90: T-Shirt | H90: Fashion | I90: 2 | J90: 700 | K90: 1400 | L90: Cash on Delivery | M90: Pending | N90: Shipped | O90: 46246 | Q90: BlueDart | T90: =IF(P90="","",P90-O90) | U90: =IF(T90="","Not Delivered",IF(T90<=0,"On Time",IF(T90<=2,"Slightly Delayed","Delayed"))) -> Not Delivered | V90: =TEXT(B90,"mmmm") -> August
A91: ORD090 | B91: 46294 | C91: C001 | D91: Arun Kumar | E91: Chennai | F91: P020 | G91: Calculator | H91: Stationery | I91: 2 | J91: 550 | K91: 1100 | L91: Net Banking | M91: Pending | N91: Cancelled | O91: 46298 | Q91: BlueDart | S91: Delivery delay | T91: =IF(P91="","",P91-O91) | U91: =IF(T91="","Not Delivered",IF(T91<=0,"On Time",IF(T91<=2,"Slightly Delayed","Delayed"))) -> Not Delivered | V91: =TEXT(B91,"mmmm") -> September
A92: ORD091 | B92: 46218 | C92: C014 | D92: Lavanya | E92: Tenkasi | F92: P003 | G92: Bluetooth Speaker | H92: Electronics | I92: 2 | J92: 1450 | K92: 2900 | L92: Credit Card | M92: Pending | N92: Delivered | O92: 46224 | P92: 46223 | Q92: Ecom Express | T92: =IF(P92="","",P92-O92) -> -1 | U92: =IF(T92="","Not Delivered",IF(T92<=0,"On Time",IF(T92<=2,"Slightly Delayed","Delayed"))) -> On Time | V92: =TEXT(B92,"mmmm") -> July
A93: ORD092 | B93: 46257 | C93: C010 | D93: Asha | E93: Madurai | F93: P017 | G93: Notebook | H93: Stationery | I93: 3 | J93: 180 | K93: 540 | L93: Cash on Delivery | M93: Paid | N93: Delivered | O93: 46263 | P93: 46264 | Q93: Delhivery | T93: =IF(P93="","",P93-O93) -> 1 | U93: =IF(T93="","Not Delivered",IF(T93<=0,"On Time",IF(T93<=2,"Slightly Delayed","Delayed"))) -> Slightly Delayed | V93: =TEXT(B93,"mmmm") -> August
A94: ORD093 | B94: 46212 | C94: C013 | D94: Dinesh | E94: Tirunelveli | F94: P007 | G94: Smart Watch | H94: Electronics | I94: 2 | J94: 2500 | K94: 5000 | L94: Debit Card | M94: Paid | N94: Out for Delivery | O94: 46217 | Q94: DTDC | T94: =IF(P94="","",P94-O94) | U94: =IF(T94="","Not Delivered",IF(T94<=0,"On Time",IF(T94<=2,"Slightly Delayed","Delayed"))) -> Not Delivered | V94: =TEXT(B94,"mmmm") -> July
A95: ORD094 | B95: 46279 | C95: C001 | D95: Arun Kumar | E95: Chennai | F95: P010 | G95: Jeans | H95: Fashion | I95: 3 | J95: 1400 | K95: 4200 | L95: Credit Card | M95: Paid | N95: Delivered | O95: 46286 | P95: 46288 | Q95: Ecom Express | T95: =IF(P95="","",P95-O95) -> 2 | U95: =IF(T95="","Not Delivered",IF(T95<=0,"On Time",IF(T95<=2,"Slightly Delayed","Delayed"))) -> Slightly Delayed | V95: =TEXT(B95,"mmmm") -> September
A96: ORD095 | B96: 46246 | C96: C018 | D96: Harini | E96: Coimbatore | F96: P016 | G96: Storage Box | H96: Home & Kitchen | I96: 3 | J96: 750 | K96: 2250 | L96: Cash on Delivery | M96: Pending | N96: Confirmed | O96: 46253 | Q96: Ecom Express | T96: =IF(P96="","",P96-O96) | U96: =IF(T96="","Not Delivered",IF(T96<=0,"On Time",IF(T96<=2,"Slightly Delayed","Delayed"))) -> Not Delivered | V96: =TEXT(B96,"mmmm") -> August
A97: ORD096 | B97: 46277 | C97: C011 | D97: Manoj | E97: Coimbatore | F97: P007 | G97: Smart Watch | H97: Electronics | I97: 2 | J97: 2500 | K97: 5000 | L97: UPI | M97: Paid | N97: Delivered | O97: 46283 | P97: 46283 | Q97: DTDC | T97: =IF(P97="","",P97-O97) -> 0 | U97: =IF(T97="","Not Delivered",IF(T97<=0,"On Time",IF(T97<=2,"Slightly Delayed","Delayed"))) -> On Time | V97: =TEXT(B97,"mmmm") -> September
A98: ORD097 | B98: 46288 | C98: C016 | D98: Pavithra | E98: Madurai | F98: P013 | G98: Bedsheet | H98: Home & Kitchen | I98: 4 | J98: 950 | K98: 3800 | L98: Credit Card | M98: Paid | N98: Delivered | O98: 46292 | P98: 46293 | Q98: DTDC | T98: =IF(P98="","",P98-O98) -> 1 | U98: =IF(T98="","Not Delivered",IF(T98<=0,"On Time",IF(T98<=2,"Slightly Delayed","Delayed"))) -> Slightly Delayed | V98: =TEXT(B98,"mmmm") -> September
A99: ORD098 | B99: 46271 | C99: C004 | D99: Divya | E99: Trichy | F99: P015 | G99: Cookware Set | H99: Home & Kitchen | I99: 1 | J99: 3200 | K99: 3200 | L99: Credit Card | M99: Failed | N99: Cancelled | O99: 46277 | Q99: Ecom Express | S99: Payment issue | T99: =IF(P99="","",P99-O99) | U99: =IF(T99="","Not Delivered",IF(T99<=0,"On Time",IF(T99<=2,"Slightly Delayed","Delayed"))) -> Not Delivered | V99: =TEXT(B99,"mmmm") -> September
A100: ORD099 | B100: 46247 | C100: C003 | D100: Rahul | E100: Coimbatore | F100: P016 | G100: Storage Box | H100: Home & Kitchen | I100: 3 | J100: 750 | K100: 2250 | L100: UPI | M100: Paid | N100: Delivered | O100: 46254 | P100: 46256 | Q100: DTDC | T100: =IF(P100="","",P100-O100) -> 2 | U100: =IF(T100="","Not Delivered",IF(T100<=0,"On Time",IF(T100<=2,"Slightly Delayed","Delayed"))) -> Slightly Delayed | V100: =TEXT(B100,"mmmm") -> August
...

Sheet pivot category_sales
A3: Row Labels | B3: Sum of Total_Amount
A4: Electronics | B4: 254750
A5: Fashion | B5: 178550
A6: Home & Kitchen | B6: 150450
A7: Stationery | B7: 25970
A8: Grand Total | B8: 609720

Sheet Pivot City_wise_order
A3: Row Labels | B3: Count of Order_ID
A4: Chennai | B4: 29
A5: Coimbatore | B5: 31
A6: Erode | B6: 16
A7: Salem | B7: 28
A8: Tenkasi | B8: 20
A9: Tirunelveli | B9: 30
A10: Trichy | B10: 15
A11: Madurai | B11: 31
A12: Grand Total | B12: 200

Sheet Pivot payment_analysis
A3: Row Labels | B3: Count of Order_ID
A4: Cash on Delivery | B4: 46
A5: Credit Card | B5: 35
A6: Debit Card | B6: 49
A7: Net Banking | B7: 32
A8: UPI | B8: 38
A9: Grand Total | B9: 200

Sheet Pivot Delivery_Analysis
A3: Row Labels | B3: Count of Order_ID
A4: Delayed | B4: 13
A5: Not Delivered | B5: 72
A6: On Time | B6: 58
A7: Slightly Delayed | B7: 57
A8: Grand Total | B8: 200

Sheet Pivot_Order_Status
A3: Row Labels | B3: Count of Order_ID
A4: Cancelled | B4: 15
A5: Confirmed | B5: 10
A6: Delivered | B6: 115
A7: Out for Delivery | B7: 15
A8: Placed | B8: 8
A9: Returned | B9: 12
A10: Shipped | B10: 25
A11: Grand Total | B11: 200

Sheet Pivot_Reasons
A3: Row Labels | B3: Count of Order_ID | D3: Row Labels | E3: Count of Order_ID
A4: Damaged product | B4: 3 | D4: Customer changed mind | E4: 2
A5: Product not as expected | B5: 4 | D5: Delivery delay | E5: 4
A6: Size issue | B6: 2 | D6: Duplicate order | E6: 3
A7: Wrong product | B7: 3 | D7: Payment issue | E7: 3
A8: Grand Total | B8: 12 | D8: Product unavailable | E8: 3
D9: Grand Total | E9: 15

Sheet pivot monthly revenue
A3: Row Labels | B3: Sum of Total_Amount
A4: July | B4: 196730
A5: August | B5: 166000
A6: September | B6: 246990
A7: Grand Total | B7: 609720

Sheet Analysis
A1: Metric | B1: Value
A2: Total Orders | B2: =COUNTA(Cleaned_Data!A2:A201) -> 200
A3: Total Revenue | B3: =SUM(Cleaned_Data!K2:K201) -> 609720
A4: Delivered Orders | B4: =COUNTIF(Cleaned_Data!N2:N201,"Delivered") -> 115
A5: Cancelled Orders | B5: =COUNTIF(Cleaned_Data!N2:N201,"Cancelled") -> 15
A6: Returned Orders | B6: =COUNTIF(Cleaned_Data!N2:N201,"Returned") -> 12
A7: Average Delay (Days) | B7: =AVERAGE(Cleaned_Data!T2:T201) -> 0.703125
A8: Cancellation Rate | B8: =B5/B2 -> 0.075
A9: Returned Rate | B9: =B6/B2 -> 0.06
A10: Delivered % | B10: =B4/B2 -> 0.575
A11: On-Time Delivery | B11: =COUNTIF(Cleaned_Data!U2:U201,"On Time")/COUNT(Cleaned_Data!T2:T201) -> 0.453125

Sheet Dashboard
A1: SALES & DELIVERY ANALYTICS DASHBOARD
